media_thumbnailer/__init__.py
media_thumbnailer/__main__.py
media_thumbnailer/formatting.py
media_thumbnailer/probing.py
media_thumbnailer/resources/iosevka-extended-extrabold.ttf
media_thumbnailer-1.0.1.dist-info/entry_points.txt
media_thumbnailer-1.0.1.dist-info/WHEEL
media_thumbnailer-1.0.1.dist-info/METADATA
media_thumbnailer-1.0.1.dist-info/RECORD
